autoselenium/__init__.py
autoselenium/browsers.py
autoselenium/download.py
autoselenium/driver.py
autoselenium/utils.py
autoselenium/whapbot.py
auto_selenium-1.0.1.dist-info/LICENSE
auto_selenium-1.0.1.dist-info/METADATA
auto_selenium-1.0.1.dist-info/WHEEL
auto_selenium-1.0.1.dist-info/top_level.txt
auto_selenium-1.0.1.dist-info/RECORD
