Metadata-Version: 2.1
Name: auto-selenium
Version: 1.0.1
Summary: Python tool to automate the download of Selenium Web Drivers for all browsers
Home-page: https://github.com/saizk/auto-selenium
Author: saizk
Author-email: sergioaizcorbe@hotmail.com
License: UNKNOWN
Project-URL: Bug Tracker, https://github.com/saizk/auto-selenium/issues
Platform: UNKNOWN
Classifier: Programming Language :: Python :: 3
Classifier: Programming Language :: Python :: 3.6
Classifier: Programming Language :: Python :: 3.7
Classifier: Programming Language :: Python :: 3.8
Classifier: Programming Language :: Python :: 3.9
Classifier: License :: OSI Approved :: MIT License
Classifier: Operating System :: OS Independent
Requires-Python: >=3.6
License-File: LICENSE
Requires-Dist: selenium (>=3.141.0)
Requires-Dist: msedge-selenium-tools (>=3.141.3)
Requires-Dist: Jinja2 (>=3.0.2)
